odoo/addons/account_peppol_send_attachment/README.rst
odoo/addons/account_peppol_send_attachment/__init__.py
odoo/addons/account_peppol_send_attachment/__manifest__.py
odoo/addons/account_peppol_send_attachment/models/__init__.py
odoo/addons/account_peppol_send_attachment/models/account_move.py
odoo/addons/account_peppol_send_attachment/readme/CONTRIBUTORS.md
odoo/addons/account_peppol_send_attachment/readme/CREDITS.md
odoo/addons/account_peppol_send_attachment/readme/DESCRIPTION.md
odoo/addons/account_peppol_send_attachment/static/description/icon.png
odoo/addons/account_peppol_send_attachment/static/description/index.html
odoo/addons/account_peppol_send_attachment/wizards/__init__.py
odoo/addons/account_peppol_send_attachment/wizards/account_invoice_send.py
odoo/addons/account_peppol_send_attachment/wizards/account_invoice_send.xml
odoo_addon_account_peppol_send_attachment-16.0.1.0.0.1.dist-info/METADATA
odoo_addon_account_peppol_send_attachment-16.0.1.0.0.1.dist-info/WHEEL
odoo_addon_account_peppol_send_attachment-16.0.1.0.0.1.dist-info/top_level.txt
odoo_addon_account_peppol_send_attachment-16.0.1.0.0.1.dist-info/RECORD
