Metadata-Version: 2.1
Name: odoo-addon-account_peppol_send_attachment
Version: 16.0.1.0.0.1
Requires-Python: >=3.10
Requires-Dist: odoo-addon-account_peppol_send_format_odoo>=16.0dev,<16.1dev
Requires-Dist: odoo>=16.0a,<16.1dev
Summary: Allow to link attachments to be sent to be peppol alongside the PDF report
Home-page: https://github.com/acsone/odoo-peppol-backport
License: AGPL-3
Author: ACSONE SA/NV,Odoo Community Association (OCA)
Author-email: support@odoo-community.org
Classifier: Programming Language :: Python
Classifier: Framework :: Odoo
Classifier: Framework :: Odoo :: 16.0
Classifier: License :: OSI Approved :: GNU Affero General Public License v3
